opshin/__init__.py
opshin/__main__.py
opshin/bridge.py
opshin/builder.py
opshin/compiler.py
opshin/compiler_config.py
opshin/fun_impls.py
opshin/prelude.py
opshin/type_impls.py
opshin/type_inference.py
opshin/typed_ast.py
opshin/util.py
opshin/ledger/__init__.py
opshin/ledger/api_v3.py
opshin/ledger/interval.py
opshin/optimize/__init__.py
opshin/optimize/optimize_const_folding.py
opshin/optimize/optimize_remove_deadconstants.py
opshin/optimize/optimize_remove_deadvars.py
opshin/optimize/optimize_remove_pass.py
opshin/optimize/optimize_remove_trace.py
opshin/optimize/optimize_union_expansion.py
opshin/rewrite/__init__.py
opshin/rewrite/rewrite_assert_none.py
opshin/rewrite/rewrite_augassign.py
opshin/rewrite/rewrite_cast_condition.py
opshin/rewrite/rewrite_comparison_chaining.py
opshin/rewrite/rewrite_empty_dicts.py
opshin/rewrite/rewrite_empty_lists.py
opshin/rewrite/rewrite_forbidden_overwrites.py
opshin/rewrite/rewrite_forbidden_return.py
opshin/rewrite/rewrite_import.py
opshin/rewrite/rewrite_import_bls12_381.py
opshin/rewrite/rewrite_import_dataclasses.py
opshin/rewrite/rewrite_import_hashlib.py
opshin/rewrite/rewrite_import_integrity_check.py
opshin/rewrite/rewrite_import_plutusdata.py
opshin/rewrite/rewrite_import_typing.py
opshin/rewrite/rewrite_import_uplc_builtins.py
opshin/rewrite/rewrite_inject_builtins.py
opshin/rewrite/rewrite_orig_name.py
opshin/rewrite/rewrite_remove_type_stuff.py
opshin/rewrite/rewrite_scoping.py
opshin/rewrite/rewrite_subscript38.py
opshin/rewrite/rewrite_tuple_assign.py
opshin/std/__init__.py
opshin/std/bitmap.py
opshin/std/bls12_381.py
opshin/std/builtins.py
opshin/std/fractions.py
opshin/std/hashlib.py
opshin/std/integrity.py
opshin/std/math.py
opshin-0.27.1.dist-info/METADATA
opshin-0.27.1.dist-info/WHEEL
opshin-0.27.1.dist-info/entry_points.txt
opshin-0.27.1.dist-info/licenses/LICENSE.txt
opshin-0.27.1.dist-info/RECORD
