Metadata-Version: 2.4
Name: opshin
Version: 0.27.1
Summary: A simple pythonic programming language for Smart Contracts on Cardano
Project-URL: Repository, https://github.com/opshin/opshin
Project-URL: Documentation, https://opshin.opshin.dev/
Author-email: nielstron <niels@opshin.dev>
License-Expression: MIT
License-File: LICENSE.txt
Keywords: cardano,compiler,language,programming-language,python,smart-contracts,validator
Classifier: Development Status :: 3 - Alpha
Classifier: Intended Audience :: Developers
Classifier: License :: OSI Approved :: MIT License
Classifier: Programming Language :: Python :: 3.9
Classifier: Programming Language :: Python :: 3.10
Classifier: Programming Language :: Python :: 3.11
Classifier: Programming Language :: Python :: 3.12
Classifier: Programming Language :: Python :: 3.13
Classifier: Topic :: Software Development :: Compilers
Requires-Python: <4.0,>=3.9.0
Requires-Dist: frozenlist2>=1.0.0
Requires-Dist: ordered-set>=4.1.0
Requires-Dist: pluthon>=1.3.5
Requires-Dist: pycardano>=0.13.0
Requires-Dist: uplc>=1.3.1
